mrbenn_panel/__init__.py
mrbenn_panel/admin.py
mrbenn_panel/apps.py
mrbenn_panel/panel.py
mrbenn_panel/tests.py
mrbenn_panel/views.py
mrbenn_panel/templates/mrbenn_panel/mrbenn_panel.html
mrbenn_panel/templates/mrbenn_panel/mrbenn_title.html
tests/__init__.py
tests/settings.py
tests/test_mrbenn.py
tests/urls.py
mrbenn_toolbar_plugin-0.0.2.dist-info/METADATA
mrbenn_toolbar_plugin-0.0.2.dist-info/WHEEL
mrbenn_toolbar_plugin-0.0.2.dist-info/top_level.txt
mrbenn_toolbar_plugin-0.0.2.dist-info/RECORD
