Metadata-Version: 2.1
Name: mrbenn-toolbar-plugin
Version: 0.0.2
Summary: An addon for Django Debug Toolbar that allows for directly opening static files and views
Home-page: https://github.com/andytwoods/mrbenn
Author: Andy Woods
Author-email: Andy Woods <andytwoods@gmail.com>
License: MIT
Classifier: Environment :: Web Environment
Classifier: Framework :: Django
Classifier: Framework :: Django :: 3.2
Classifier: Intended Audience :: Developers
Classifier: License :: OSI Approved :: BSD License
Classifier: Operating System :: OS Independent
Classifier: Programming Language :: Python
Classifier: Programming Language :: Python :: 3
Classifier: Programming Language :: Python :: 3 :: Only
Classifier: Programming Language :: Python :: 3.6
Classifier: Programming Language :: Python :: 3.7
Classifier: Programming Language :: Python :: 3.8
Classifier: Programming Language :: Python :: 3.9
Classifier: Programming Language :: Python :: 3.10
Classifier: Topic :: Internet :: WWW/HTTP
Classifier: Topic :: Internet :: WWW/HTTP :: Dynamic Content
Requires-Python: >=3.6
Requires-Dist: Django >=2.2
Requires-Dist: django-debug-toolbar >=3.2.1
